{"AB": ["bc", "cc", "dc", "bd", "eb", "ae", "af", "ag", "bg", "cf", "ch", "dg", "dh", "di", "ei", "fg", "gi", "hh", "ih", "ii", "jj", "kj", "lj", "ki", "kh", "lh", "mh", "nh", "oh", "ld", "lc", "qd", "qe", "rc", "pf", "pi", "qi", "qk", "ql", "qm", "ol", "nl", "nk", "mk", "ll", "kp", "lp", "mp", "np", "ip", "hq", "pq", "qp"], "AW": ["ec", "fc", "gc", "dd", "cd", "ee", "ce", "be", "bf", "bh", "bi", "ci", "dj", "dk", "dq", "co", "gj", "hj", "hi", "ij", "ik", "jk", "kk", "lk", "ji", "jh", "jg", "kg", "if", "id", "mf", "nd", "mc", "pd", "qc", "qb", "rb", "oi", "ni", "mi", "li", "pj", "ok", "pl", "ml", "mm", "mo", "on", "po", "qo", "ko", "jo"], "SZ": "19", "C": "Black to play", "SOL": [["B", "ga", "", ""]]}