{"AB": ["dd", "jc", "lc", "ld", "md", "ne", "oe", "pf", "pg", "pd", "qd", "rd", "rc", "cp", "bo", "bq", "ar", "eo", "en", "em", "fl", "gl", "il", "jk", "jm", "kn", "mo", "hn", "ip", "iq", "jq", "gq", "fq", "er", "dr", "kr", "lq", "mr", "nq", "pp"], "AW": ["br", "cr", "cq", "dq", "eq", "ep", "fp", "gp", "fo", "fn", "gm", "hm", "im", "io", "jo", "jp", "kp", "kq", "qn", "qk", "rb", "qc", "pc", "nd", "nc", "mc", "og", "ph", "qh", "me", "mf", "mh"], "SZ": 19, "C": "Black to play", "SOL": [["B", "oc", "", ""]]}