{"AB": ["pd", "qd", "oe", "nc", "ld", "kd", "kb", "ja", "ib", "id", "hd", "ie", "ge", "gf", "gg", "ef", "de", "ce", "ch", "ih", "kh", "lh", "mh", "oh", "qh", "co", "dp", "fp", "hq", "jq", "lq", "np", "op", "pp", "jo", "jm", "jk"], "AW": ["rf", "pf", "of", "nf", "lf", "lg", "hf", "he", "je", "jf", "if", "hc", "hb", "ha", "ia", "gd", "fd", "fe", "cd", "dc", "cj", "cn", "dn", "ho", "hm", "hk", "ij", "jj", "lk", "lm", "lo", "oo", "qn", "rp", "qq"], "SZ": 19, "C": "White to play", "SOL": [["W", "jd", "", ""]]}